[
  {
    "id": "san-andres",
    "activo": true,
    "destino": "San Andrés",
    "emoji": "🌴",
    "badge": "🔥 SÚPER OFERTA",
    "copy": "El mar más azul de Colombia. Arena blanca, buzos de colores y puestas de sol que te dejan sin palabras.",
    "imagen": "/assets/img/sanandres.jpg",
    "precioDesde": 890000,
    "moneda": "COP",
    "descripcionPrecio": "por persona",
    "incluye": "Vuelo + 3 noches + traslados",
    "vigencia": "Hasta el 30 de julio",
    "heroSlide": true,
    "whatsappMensaje": "Hola Emitours 👋, vi la oferta de *San Andrés* en su web y quiero cotizar. ¿Cuándo hay disponibilidad? ✈️"
  },
  {
    "id": "cartagena",
    "activo": true,
    "destino": "Cartagena",
    "emoji": "🏰",
    "badge": "⭐ MÁS VENDIDO",
    "copy": "Ciudad amurallada, historia viva y playas tropicales. El destino perfecto para enamorarse de Colombia.",
    "imagen": "/assets/img/cartagena.jpg",
    "precioDesde": 750000,
    "moneda": "COP",
    "descripcionPrecio": "por persona",
    "incluye": "Vuelo + hotel + city tour",
    "vigencia": "Todo el año",
    "heroSlide": true,
    "whatsappMensaje": "Hola Emitours 👋, vi la oferta de *Cartagena* en su web y quiero cotizar. ¿Cuándo hay disponibilidad? ✈️"
  },
  {
    "id": "santa-marta",
    "activo": true,
    "destino": "Santa Marta",
    "emoji": "🌊",
    "badge": null,
    "copy": "Tayrona, la Sierra Nevada y las mejores playas del Caribe colombiano en un solo destino.",
    "imagen": "/assets/img/santamarta.jpg",
    "precioDesde": 680000,
    "moneda": "COP",
    "descripcionPrecio": "por persona",
    "incluye": "Vuelo + 2 noches",
    "vigencia": null,
    "heroSlide": false,
    "whatsappMensaje": "Hola Emitours 👋, vi la oferta de *Santa Marta* en su web y quiero cotizar. ¿Cuándo hay disponibilidad? ✈️"
  },
  {
    "id": "punta-cana",
    "activo": true,
    "destino": "Punta Cana",
    "emoji": "🌺",
    "badge": "✈️ TODO INCLUIDO",
    "copy": "Resorts todo incluido, playas vírgenes y la energía del Caribe en su máximo esplendor.",
    "imagen": "/assets/img/puntacana.jpg",
    "precioDesde": 7200000,
    "moneda": "COP",
    "descripcionPrecio": "por persona",
    "incluye": "Vuelo + resort 5★ all inclusive",
    "vigencia": "Salidas agosto–diciembre",
    "heroSlide": true,
    "whatsappMensaje": "Hola Emitours 👋, vi la oferta de *Punta Cana* en su web y quiero cotizar. ¿Cuándo hay disponibilidad? ✈️"
  },
  {
    "id": "cancun",
    "activo": true,
    "destino": "Cancún",
    "emoji": "🌮",
    "badge": "💥 PRECIO ESPECIAL",
    "copy": "Playas turquesas, ruinas mayas y vida nocturna de clase mundial.",
    "imagen": "/assets/img/cancun.jpg",
    "precioDesde": 6400000,
    "moneda": "COP",
    "descripcionPrecio": "por persona",
    "incluye": "Vuelo + hotel + traslados",
    "vigencia": "Disponible todo el año",
    "heroSlide": true,
    "whatsappMensaje": "Hola Emitours 👋, vi la oferta de *Cancún* en su web y quiero cotizar. ¿Cuándo hay disponibilidad? ✈️"
  },
  {
    "id": "espana",
    "activo": true,
    "destino": "España",
    "emoji": "🇪🇸",
    "badge": null,
    "copy": "Barcelona, Madrid, Sevilla y más. Europa al alcance con asesoría migratoria incluida.",
    "imagen": "/assets/img/espana.jpg",
    "precioDesde": 12500000,
    "moneda": "COP",
    "descripcionPrecio": "por persona",
    "incluye": "Vuelo + 7 noches + asistencia migratoria",
    "vigencia": null,
    "heroSlide": true,
    "whatsappMensaje": "Hola Emitours 👋, vi la oferta de *España* en su web y quiero cotizar. ¿Cuándo hay disponibilidad? ✈️"
  },
  {
    "id": "hacienda-napoles",
    "activo": true,
    "destino": "Hacienda Nápoles",
    "emoji": "🦁",
    "badge": "🦁 PLAN FAMILIAR",
    "copy": "Aventura familiar en Antioquia. Parque temático, safaris y naturaleza selvática para todos.",
    "imagen": "/assets/img/haciendanapoles.jpg",
    "precioDesde": 420000,
    "moneda": "COP",
    "descripcionPrecio": "por persona",
    "incluye": "Transporte + entrada + 1 noche",
    "vigencia": "Fines de semana",
    "heroSlide": false,
    "whatsappMensaje": "Hola Emitours 👋, vi la oferta de *Hacienda Nápoles* en su web y quiero cotizar. ¿Cuándo hay disponibilidad? ✈️"
  }
]
