{
  "items": [
    {
      "badge": "🔥 SÚPER OFERTA",
      "emoji": "🌴",
      "destino": "San Andrés",
      "precioDesde": 890000,
      "whatsappMensaje": "Hola Emitours 👋, vi la oferta de *San Andrés* en su web y quiero cotizar. ¿Cuándo hay disponibilidad? ✈️",
      "activo": true,
      "imagen": "/assets/img/sanandres.jpg",
      "incluye": "Vuelo + 3 noches + traslados",
      "descripcionPrecio": "por persona",
      "copy": "El mar más azul de Colombia. Arena blanca, buzos de colores y puestas de sol que te dejan sin palabras.",
      "moneda": "COP",
      "heroSlide": true,
      "id": "san-andres",
      "vigencia": "Hasta el 30 de julio"
    },
    {
      "badge": "⭐ MÁS VENDIDO",
      "emoji": "🏰",
      "destino": "Cartagena",
      "precioDesde": 750000,
      "whatsappMensaje": "Hola Emitours 👋, vi la oferta de *Cartagena* en su web y quiero cotizar. ¿Cuándo hay disponibilidad? ✈️",
      "activo": true,
      "imagen": "/assets/img/cartagena.jpg",
      "incluye": "Vuelo + hotel + city tour",
      "descripcionPrecio": "por persona",
      "copy": "Ciudad amurallada, historia viva y playas tropicales. El destino perfecto para enamorarse de Colombia.",
      "moneda": "COP",
      "heroSlide": true,
      "id": "cartagena",
      "vigencia": "Todo el año"
    },
    {
      "badge": "",
      "emoji": "🌊",
      "destino": "Santa Marta",
      "precioDesde": 680000,
      "whatsappMensaje": "Hola Emitours 👋, vi la oferta de *Santa Marta* en su web y quiero cotizar. ¿Cuándo hay disponibilidad? ✈️",
      "activo": true,
      "imagen": "/assets/img/santamarta.jpg",
      "incluye": "Vuelo + 2 noches",
      "descripcionPrecio": "por persona",
      "copy": "Tayrona, la Sierra Nevada y las mejores playas del Caribe colombiano en un solo destino.",
      "moneda": "COP",
      "heroSlide": false,
      "id": "santa-marta",
      "vigencia": ""
    },
    {
      "badge": "",
      "emoji": "🌴",
      "destino": "Estados Unidos - Miami",
      "precioDesde": 2000000,
      "whatsappMensaje": "hola estoy interesado",
      "activo": true,
      "incluye": "vuelo estadia tours ",
      "descripcionPrecio": "por persona",
      "copy": "ELige ah que parte de usa ir ",
      "moneda": "COP",
      "heroSlide": false,
      "id": "estados-unidos",
      "vigencia": ""
    }
  ]
}
